anonymity_loss_coefficient/__init__.py
anonymity_loss_coefficient/alc/__init__.py
anonymity_loss_coefficient/alc/alc_manager.py
anonymity_loss_coefficient/alc/anonymity_loss_coefficient.py
anonymity_loss_coefficient/alc/baseline_predictor.py
anonymity_loss_coefficient/alc/data_files.py
anonymity_loss_coefficient/alc/defaults.py
anonymity_loss_coefficient/alc/params.py
anonymity_loss_coefficient/alc/reporting.py
anonymity_loss_coefficient/alc/score_interval.py
anonymity_loss_coefficient/attacks/__init__.py
anonymity_loss_coefficient/attacks/best_row_match/__init__.py
anonymity_loss_coefficient/attacks/best_row_match/brm_attack.py
anonymity_loss_coefficient/attacks/best_row_match/matching_routines.py
anonymity_loss_coefficient/attacks/best_row_match/temp.py
anonymity_loss_coefficient/utils/__init__.py
anonymity_loss_coefficient/utils/attack_utils.py
anonymity_loss_coefficient/utils/io_utils.py
anonymity_loss_coefficient/utils/logger_utils.py
anonymity_loss_coefficient/utils/matching_routines.py
anonymity_loss_coefficient-1.0.32.dist-info/licenses/LICENSE
anonymity_loss_coefficient-1.0.32.dist-info/METADATA
anonymity_loss_coefficient-1.0.32.dist-info/WHEEL
anonymity_loss_coefficient-1.0.32.dist-info/top_level.txt
anonymity_loss_coefficient-1.0.32.dist-info/RECORD
