Metadata-Version: 2.4
Name: anonymity_loss_coefficient
Version: 1.0.32
Summary: A package to run attacks on anonymized data using the Anonymity Loss Coefficient.
Home-page: https://github.com/yoid2000/anonymity_loss_coefficient
Author: Paul Francis
Author-email: paul@francis.com
Classifier: Programming Language :: Python :: 3
Classifier: License :: OSI Approved :: MIT License
Classifier: Operating System :: OS Independent
Requires-Python: >=3.6
License-File: LICENSE
Requires-Dist: numpy>=1.21.0
Requires-Dist: pandas>=1.3.0
Requires-Dist: scipy>=1.7.0
Requires-Dist: scikit-learn>=1.0.0
Requires-Dist: matplotlib>=3.4.0
Requires-Dist: seaborn>=0.11.0
Requires-Dist: pyarrow>=20.0.0
Requires-Dist: fastparquet>=2024.1.0
Requires-Dist: charset_normalizer>=3.0.0
Dynamic: author
Dynamic: author-email
Dynamic: classifier
Dynamic: home-page
Dynamic: license-file
Dynamic: requires-dist
Dynamic: requires-python
Dynamic: summary
